pyelasticdsl/dsl.py
pyelasticdsl/types.py
pyelasticdsl/utils.py
pyelasticdsl/query/__init__.py
pyelasticdsl/query/bool_query.py
pyelasticdsl/query/boosting_query.py
pyelasticdsl/query/exists_query.py
pyelasticdsl/query/fuzzy_query.py
pyelasticdsl/query/ids_query.py
pyelasticdsl/query/match_query.py
pyelasticdsl/query/percolator_query.py
pyelasticdsl/query/range_query.py
pyelasticdsl/query/regexp_query.py
pyelasticdsl/query/script.py
pyelasticdsl/query/term_query.py
pyelasticdsl/query/term_query_lookup.py
pyelasticdsl-0.1.0.dist-info/licenses/LICENSE
pyelasticdsl-0.1.0.dist-info/METADATA
pyelasticdsl-0.1.0.dist-info/WHEEL
pyelasticdsl-0.1.0.dist-info/top_level.txt
pyelasticdsl-0.1.0.dist-info/RECORD
