Metadata-Version: 2.4
Name: pyelasticdsl
Version: 0.1.0
Summary: A Python DSL for Elasticsearch queries
License: MIT
Project-URL: Homepage, https://github.com/AlaricZy/pyelasticdsl
Project-URL: Repository, https://github.com/AlaricZy/pyelasticdsl
Keywords: elasticsearch,dsl,query,python
Classifier: Programming Language :: Python :: 3
Classifier: License :: OSI Approved :: MIT License
Classifier: Operating System :: OS Independent
Requires-Python: >=3.12
License-File: LICENSE
Dynamic: license-file
